jupyterhub/__init__.py
jupyterhub/singleuser.py
jupyterhub/utils.py
jupyterhub/services/__init__.py
jupyterhub/services/auth.py
jupyterhub_legacy_py2_singleuser-0.7.2.data/scripts/jupyterhub-singleuser
jupyterhub_legacy_py2_singleuser-0.7.2.dist-info/DESCRIPTION.rst
jupyterhub_legacy_py2_singleuser-0.7.2.dist-info/METADATA
jupyterhub_legacy_py2_singleuser-0.7.2.dist-info/RECORD
jupyterhub_legacy_py2_singleuser-0.7.2.dist-info/WHEEL
jupyterhub_legacy_py2_singleuser-0.7.2.dist-info/metadata.json
jupyterhub_legacy_py2_singleuser-0.7.2.dist-info/top_level.txt
