Metadata-Version: 2.0
Name: jupyterhub-legacy-py2-singleuser
Version: 0.7.2
Summary: Single-user server for running Jupyter Notebooks (on Python2) with JupyterHub
Home-page: https://github.com/yuvipanda/jupyterhub-legacy-singleuser
Author: Yuvi Panda
Author-email: yuvipanda@gmail.com
License: 3 Clause BSD
Platform: UNKNOWN
Requires-Dist: jinja2
Requires-Dist: monotonic
Requires-Dist: notebook (>=4.0)
Requires-Dist: requests
Requires-Dist: tornado (>=4.1)
Requires-Dist: traitlets (>=4.1)
